instanseg/__init__.py
instanseg/benchmark/__init__.py
instanseg/benchmark/association.py
instanseg/benchmark/default.py
instanseg/benchmark/detailed.py
instanseg/benchmark/dice.py
instanseg/benchmark/iou.py
instanseg/benchmark/mean.py
instanseg/benchmark/panoptic.py
instanseg/metrics/__init__.py
instanseg/metrics/association.py
instanseg/metrics/constants.py
instanseg/metrics/full_statistics.py
instanseg/metrics/instance_based.py
instanseg/metrics/point_based.py
instanseg/utils/__init__.py
instanseg/utils/association_utils.py
instanseg/utils/check_input.py
instanseg/utils/iou_overlap.py
instanseg/utils/metrics_utils.py
instanseg-0.0.2.dist-info/LICENSE
instanseg-0.0.2.dist-info/METADATA
instanseg-0.0.2.dist-info/WHEEL
instanseg-0.0.2.dist-info/RECORD
